sped/__init__.py
sped/arquivos.py
sped/blocos.py
sped/campos.py
sped/erros.py
sped/registros.py
sped/ecd/__init__.py
sped/ecd/arquivos.py
sped/ecd/blocos.py
sped/ecd/registros.py
sped/ecd/tabelas.py
sped/ecd/tabelas/SPEDCONTABIL_CONTAS_REFERENCIAIS$SPEDCONTABIL_CONTASREF$1$198
sped/ecd/tabelas/SPEDCONTABIL_CONTAS_REFERENCIAIS$SPEDCONTABIL_CONTASREF_BACEN$1$199
sped/ecd/tabelas/SPEDCONTABIL_CONTAS_REFERENCIAIS$SPEDCONTABIL_CONTASREF_SUSEP$1$200
sped/ecd/tabelas/SPEDCONTABIL_CONTAS_REFERENCIAIS$SPEDCONTABIL_CONTASREF_TSE$1$225
sped/ecd/tabelas/SPEDCONTABIL_DINAMICO_2014$SPEDECF_DINAMICA_L100_A$13$386
sped/ecd/tabelas/SPEDCONTABIL_DINAMICO_2014$SPEDECF_DINAMICA_L100_A$6$386
sped/ecd/tabelas/SPEDCONTABIL_DINAMICO_2014$SPEDECF_DINAMICA_L100_B$4$387
sped/ecd/tabelas/SPEDCONTABIL_DINAMICO_2014$SPEDECF_DINAMICA_L100_B$6$387
sped/ecd/tabelas/SPEDCONTABIL_DINAMICO_2014$SPEDECF_DINAMICA_L100_C$4$388
sped/ecd/tabelas/SPEDCONTABIL_DINAMICO_2014$SPEDECF_DINAMICA_L300_A$4$395
sped/ecd/tabelas/SPEDCONTABIL_DINAMICO_2014$SPEDECF_DINAMICA_L300_B$1$396
sped/ecd/tabelas/SPEDCONTABIL_DINAMICO_2014$SPEDECF_DINAMICA_L300_B$2$396
sped/ecd/tabelas/SPEDCONTABIL_DINAMICO_2014$SPEDECF_DINAMICA_L300_C$1$397
sped/ecd/tabelas/SPEDCONTABIL_DINAMICO_2014$SPEDECF_DINAMICA_L300_C$2$397
sped/ecd/tabelas/SPEDCONTABIL_DINAMICO_2014$SPEDECF_DINAMICA_P100$12$389
sped/ecd/tabelas/SPEDCONTABIL_DINAMICO_2014$SPEDECF_DINAMICA_P100$3$389
sped/ecd/tabelas/SPEDCONTABIL_DINAMICO_2014$SPEDECF_DINAMICA_P150$3$398
sped/ecd/tabelas/SPEDCONTABIL_DINAMICO_2014$SPEDECF_DINAMICA_U100_A$2$390
sped/ecd/tabelas/SPEDCONTABIL_DINAMICO_2014$SPEDECF_DINAMICA_U100_B$3$391
sped/ecd/tabelas/SPEDCONTABIL_DINAMICO_2014$SPEDECF_DINAMICA_U100_B$4$391
sped/ecd/tabelas/SPEDCONTABIL_DINAMICO_2014$SPEDECF_DINAMICA_U100_C$2$392
sped/ecd/tabelas/SPEDCONTABIL_DINAMICO_2014$SPEDECF_DINAMICA_U100_D$3$393
sped/ecd/tabelas/SPEDCONTABIL_DINAMICO_2014$SPEDECF_DINAMICA_U100_D$7$393
sped-0.4.5.dist-info/DESCRIPTION.rst
sped-0.4.5.dist-info/METADATA
sped-0.4.5.dist-info/RECORD
sped-0.4.5.dist-info/WHEEL
sped-0.4.5.dist-info/metadata.json
sped-0.4.5.dist-info/top_level.txt
