Metadata-Version: 2.0
Name: sped
Version: 0.4.5
Summary: Biblioteca para geração dos arquivos do Sistema Público de Escrituração Digital (SPED) para Python.
Home-page: https://github.com/sped-br/python-sped
Author: Sergio Garcia
Author-email: sergio@ginx.com.br
License: MIT
Download-URL: https://github.com/sped-br/python-sped/releases
Keywords: sped fiscal contábil contabilidade receita federal
Platform: UNKNOWN
Classifier: Development Status :: 3 - Alpha
Classifier: Intended Audience :: Developers
Classifier: License :: OSI Approved :: MIT License
Classifier: Programming Language :: Python :: 2
Classifier: Programming Language :: Python :: 2.7
Classifier: Programming Language :: Python :: 3
Classifier: Programming Language :: Python :: 3.4
Requires-Dist: six
